picsellia_training/__init__.py
picsellia_training/client.py
picsellia_training/client_old.py
picsellia_training/clientv2.py
picsellia_training/pxl_exceptions.py
picsellia_training/pxl_multithreading.py
picsellia_training/pxl_urls.py
picsellia_training/pxl_urls_v2.py
picsellia_training/pxl_utils.py
picsellia_training-0.10.14.dist-info/LICENSE
picsellia_training-0.10.14.dist-info/METADATA
picsellia_training-0.10.14.dist-info/WHEEL
picsellia_training-0.10.14.dist-info/top_level.txt
picsellia_training-0.10.14.dist-info/RECORD
