Metadata-Version: 2.1
Name: picsellia-training
Version: 0.10.14
Summary: Python SDK raining module for Picsell.ia
Home-page: https://www.picsellia.com
Author: Pierre-Nicolas Tiffreau CTO @ Picsell.ia
Author-email: pierre-nicolas@picsellia.com
License: UNKNOWN
Keywords: SDK,Picsell.ia,Computer Vision,Deep Learning
Platform: UNKNOWN
Classifier: Development Status :: 3 - Alpha
Classifier: Intended Audience :: Developers
Classifier: Topic :: Software Development :: Build Tools
Classifier: License :: OSI Approved :: MIT License
Classifier: Programming Language :: Python :: 3
Classifier: Programming Language :: Python :: 3.6
Classifier: Programming Language :: Python :: 3.7
Classifier: Programming Language :: Python :: 3.8
Requires-Python: >=3.6
Requires-Dist: numpy (==1.18.5)
Requires-Dist: opencv-python (==4.4.0.44)
Requires-Dist: Pillow (==7.2.0)
Requires-Dist: requests (==2.24.0)
Requires-Dist: scipy (==1.4.1)
